argo/__init__.py
argo/argo.py
argo/core.py
argo/utils/__init__.py
argo/utils/supportdata.py
pyArgo-0.0.4.dist-info/DESCRIPTION.rst
pyArgo-0.0.4.dist-info/METADATA
pyArgo-0.0.4.dist-info/RECORD
pyArgo-0.0.4.dist-info/WHEEL
pyArgo-0.0.4.dist-info/metadata.json
pyArgo-0.0.4.dist-info/top_level.txt
