Metadata-Version: 2.0
Name: pyArgo
Version: 0.0.4
Summary: Python package to handle Argo profiles.
Home-page: https://github.com/castelao/pyArgo
Author: Guilherme Castelao
Author-email: guilherme@castelao.net
License: 3-clause BSD
Keywords: Argo oceanography
Platform: UNKNOWN
Classifier: Development Status :: 2 - Pre-Alpha
Classifier: Intended Audience :: Science/Research
Classifier: License :: OSI Approved :: BSD License
Classifier: Operating System :: OS Independent
Classifier: Programming Language :: Python :: 2.7
Classifier: Programming Language :: Python :: 3.5
Classifier: Topic :: Scientific/Engineering
Requires-Dist: netCDF4 (>=1.2.4)
